Pythactyl/Admin.py
Pythactyl/Client.py
Pythactyl/Errors.py
Pythactyl/__init__.py
Pythactyl/objects.py
Pythactyl/server.py
Pythactyl-2.18.dist-info/LICENSE
Pythactyl-2.18.dist-info/METADATA
Pythactyl-2.18.dist-info/WHEEL
Pythactyl-2.18.dist-info/entry_points.txt
Pythactyl-2.18.dist-info/top_level.txt
Pythactyl-2.18.dist-info/RECORD
