Metadata-Version: 2.1
Name: Pythactyl
Version: 2.18
Summary: Pterodactyl panel API wrapper
Home-page: https://github.com/iamgadget/Pythactyl
Author: IAmGadget
Author-email: info@iamgadget.co.uk
License: MIT
Platform: UNKNOWN
Classifier: License :: OSI Approved :: MIT License
Classifier: Programming Language :: Python :: 3
Classifier: Programming Language :: Python :: 3.7
License-File: LICENSE
Requires-Dist: requests
